testing.kafka-0.0.1-py3.7-nspkg.pth
testing/kafka.py
testing/zookeeper.py
testing.kafka-0.0.1.dist-info/METADATA
testing.kafka-0.0.1.dist-info/WHEEL
testing.kafka-0.0.1.dist-info/namespace_packages.txt
testing.kafka-0.0.1.dist-info/top_level.txt
testing.kafka-0.0.1.dist-info/RECORD
